{
    "uuid": [
        {
            "value": "1a7aa356-1505-440e-ac78-7ea516c3c1e5"
        }
    ],
    "langcode": [
        {
            "value": "en"
        }
    ],
    "uid": [],
    "filename": [
        {
            "value": "victoria-sponge-umami.jpg"
        }
    ],
    "uri": [
        {
            "value": "public:\/\/victoria-sponge-umami.jpg"
        }
    ],
    "filemime": [
        {
            "value": "image\/jpeg"
        }
    ],
    "filesize": [
        {
            "value": 65418
        }
    ],
    "status": [
        {
            "value": true
        }
    ],
    "created": [
        {
            "value": "2022-09-12T00:53:14+00:00",
            "format": "Y-m-d\\TH:i:sP"
        }
    ],
    "changed": [
        {
            "value": "2022-09-12T00:53:14+00:00",
            "format": "Y-m-d\\TH:i:sP"
        }
    ]
}