{
    "uuid": [
        {
            "value": "345dac77-27f4-474d-895e-7fb89ad7f2b3"
        }
    ],
    "langcode": [
        {
            "value": "es"
        }
    ],
    "bundle": [
        {
            "target_id": "image",
            "target_type": "media_type",
            "target_uuid": "d1c6573b-1e62-435d-be93-2349a43cb78e"
        }
    ],
    "revision_created": [
        {
            "value": "2022-09-12T00:53:14+00:00",
            "format": "Y-m-d\\TH:i:sP"
        }
    ],
    "revision_user": [],
    "revision_log_message": [],
    "status": [
        {
            "value": true
        }
    ],
    "uid": [
        {
            "target_type": "user",
            "target_uuid": "2b2cba1b-9a87-4940-adb0-13818cd1cccf"
        }
    ],
    "name": [
        {
            "value": "Delicioso chocolate sin lactosa"
        }
    ],
    "thumbnail": [
        {
            "alt": "Deliciosa tableta de chocolate con leche sin lactosa partido en onzas.",
            "title": null,
            "width": 768,
            "height": 511,
            "target_type": "file",
            "target_uuid": "0f79205a-dfff-4942-971f-b8137b9f20db"
        }
    ],
    "created": [
        {
            "value": "2022-09-12T00:53:14+00:00",
            "format": "Y-m-d\\TH:i:sP"
        }
    ],
    "changed": [
        {
            "value": "2022-09-12T00:53:14+00:00",
            "format": "Y-m-d\\TH:i:sP"
        }
    ],
    "default_langcode": [
        {
            "value": false
        }
    ],
    "revision_translation_affected": [
        {
            "value": true
        }
    ],
    "path": [
        {
            "alias": null,
            "pid": null,
            "langcode": "es"
        }
    ],
    "content_translation_source": [
        {
            "value": "und"
        }
    ],
    "content_translation_outdated": [
        {
            "value": false
        }
    ],
    "field_media_image": [
        {
            "alt": "Deliciosa tableta de chocolate con leche sin lactosa partido en onzas.",
            "title": null,
            "width": 768,
            "height": 511,
            "target_type": "file",
            "target_uuid": "bcb3cee5-d090-4e79-97e2-ba47229c3d19"
        }
    ]
}